haltonseq/__init__.py
haltonseq/core.py
haltonseq-0.2.0.dist-info/METADATA
haltonseq-0.2.0.dist-info/WHEEL
haltonseq-0.2.0.dist-info/top_level.txt
haltonseq-0.2.0.dist-info/RECORD
