Metadata-Version: 2.4
Name: haltonseq
Version: 0.2.0
Summary: Simple Halton sequence generator
Author-email: robert <robert@valassi.se>
License: MIT
Project-URL: Homepage, https://github.com/cogitoEdge/haltonseq
Requires-Python: >=3.8
